LICENSE
README.md
setup.cfg
setup.py
palazzetti_sdk_local_api/__init__.py
palazzetti_sdk_local_api/exceptions.py
palazzetti_sdk_local_api.egg-info/PKG-INFO
palazzetti_sdk_local_api.egg-info/SOURCES.txt
palazzetti_sdk_local_api.egg-info/dependency_links.txt
palazzetti_sdk_local_api.egg-info/requires.txt
palazzetti_sdk_local_api.egg-info/top_level.txt