Metadata-Version: 2.1
Name: palazzetti-sdk-local-api
Version: 1.0.14
Summary: IoT Device Communication Library
Home-page: https://github.com/marcopal74/palazzetti_local_api
Author: Marco Palazzetti
Author-email: marco.palazzetti@me.com
License: UNKNOWN
Platform: UNKNOWN
Requires-Python: >=3.6
License-File: LICENSE
